Homework3/CPU/codes/data_memory.v
module data_memory #(
	parameter ADDR_W = 64,
	parameter DATA_W = 64
)(
	input               i_clk,
	input               i_rst_n,
	input  [DATA_W-1:0] i_data,
	input  [ADDR_W-1:0] i_addr,
	input               i_MemRead,
	input               i_MemWrite,
	output              o_valid,
	output [DATA_W-1:0] o_data
);

	reg [7:0] mem   [0:1023];
	reg [7:0] mem_w [0:1023];
	reg              o_valid_r, o_valid_w;
	reg [DATA_W-1:0] o_data_r,  o_data_w;
	reg        [3:0] cs, ns;
	reg [ADDR_W-1:0] temp_addr, temp_addr_w;
	reg [DATA_W-1:0] temp_data, temp_data_w;
	reg              temp_MemRead, temp_MemRead_w;
	reg              temp_MemWrite, temp_MemWrite_w;

	wire i_valid;

	integer i;

	assign o_valid = o_valid_r;
	assign o_data  = o_data_r;
	assign i_valid = i_MemRead | i_MemWrite;

	always @(*) begin
		if (i_valid) begin
			temp_addr_w     = i_addr;
			temp_data_w     = i_data;
			temp_MemRead_w  = i_MemRead;
			temp_MemWrite_w = i_MemWrite;
		end else begin
			temp_addr_w     = temp_addr;
			temp_data_w     = temp_data;
			temp_MemRead_w  = temp_MemRead;
			temp_MemWrite_w = temp_MemWrite;
		end
	end

	always @(*) begin
		if (cs == 7 && temp_MemRead) begin
			o_valid_w = 1;
			o_data_w  = {mem[temp_addr+7], mem[temp_addr+6],
						 mem[temp_addr+5], mem[temp_addr+4],
						 mem[temp_addr+3], mem[temp_addr+2],
						 mem[temp_addr+1], mem[temp_addr+0]};
			temp_MemRead_w   = 0;
			temp_MemWrite_w  = 0;
			temp_data_w      = 0;
			temp_addr_w      = 0;
		end else if (cs == 7 && temp_MemWrite) begin
			mem_w[temp_addr+0] = temp_data[ 7:0];
			mem_w[temp_addr+1] = temp_data[15:8];
			mem_w[temp_addr+2] = temp_data[23:16];
			mem_w[temp_addr+3] = temp_data[31:24];
			mem_w[temp_addr+4] = temp_data[39:32];
			mem_w[temp_addr+5] = temp_data[47:40];
			mem_w[temp_addr+6] = temp_data[55:48];
			mem_w[temp_addr+7] = temp_data[63:56];
			o_valid_w        = 0;
			temp_MemRead_w   = 0;
			temp_MemWrite_w  = 0;
			temp_data_w      = 0;
			temp_addr_w      = 0;
		end else begin
			for (i=0; i<1024; i++)
				mem_w[i] <= mem[i];
			o_valid_w = 0;
			o_data_w  = 0;
		end
	end

	always @(*) begin
		case (cs)
			0: ns = (i_valid) ? 1 : 0;
			1: ns = 2;
			2: ns = 3;
			3: ns = 4;
			4: ns = 5;
			5: ns = 6;
			6: ns = 7;
			7: ns = 0;
		endcase
	end

	always @(posedge i_clk or negedge i_rst_n) begin
		if (~i_rst_n) begin
			o_valid_r     <= 0;
			o_data_r      <= 0;
			cs            <= 0;
			temp_addr     <= 0;
			temp_data     <= 0;
			temp_MemRead  <= 0;
			temp_MemWrite <= 0;
			for (i=0; i<1024; i++)
				mem[i] <= 0;
		end else begin
			o_valid_r     <= o_valid_w;
			o_data_r      <= o_data_w;
			cs            <= ns;
			temp_addr     <= temp_addr_w;
			temp_data     <= temp_data_w;
			temp_MemRead  <= temp_MemRead_w;
			temp_MemWrite <= temp_MemWrite_w;
			for (i=0; i<1024; i++)
				mem[i] <= mem_w[i];
		end
	end

endmodule

Homework3/CPU/codes/instruction_memory.v
module instruction_memory #(
	parameter ADDR_W   = 64,
	parameter INST_W   = 32,
	parameter MAX_INST = 16
)(
	input               i_clk,
	input               i_rst_n,
	input               i_valid,
	input  [ADDR_W-1:0] i_addr,
	output              o_valid,
	output [INST_W-1:0] o_inst
);

	reg [INST_W-1:0] mem [0:MAX_INST-1];
	reg              o_valid_r, o_valid_w;
	reg [INST_W-1:0] o_inst_r,  o_inst_w;
	reg        [3:0] cs, ns;
	reg [ADDR_W-1:0] temp_addr_r, temp_addr_w;
	integer i;

	assign o_valid = o_valid_r;
	assign o_inst  = o_inst_r;

	always @(*) begin
		if (i_valid) begin
			temp_addr_w = i_addr;
		end else begin
			temp_addr_w = temp_addr_r;
		end
	end

	always @(*) begin
		if (cs == 5) begin
			o_valid_w = 1;
			o_inst_w  = mem[temp_addr_r/4];
		end else begin
			o_valid_w = 0;
			o_inst_w  = 0;
		end
	end

	always @(*) begin
		case (cs)
			0: ns = (i_valid) ? 1 : 0;
			1: ns = 2;
			2: ns = 3;
			3: ns = 4;
			4: ns = 5;
			5: ns = 0;
		endcase
	end

	always @(posedge i_clk or negedge i_rst_n) begin
		if (~i_rst_n) begin
			o_valid_r   <= 0;
			o_inst_r    <= 0;
			cs          <= 0;
			temp_addr_r <= 0;
		end else begin
			o_valid_r   <= o_valid_w;
			o_inst_r    <= o_inst_w;
			cs          <= ns;
			temp_addr_r <= temp_addr_w;
		end
	end

endmodule

Homework3/CPU/codes/cpu.v
module cpu #( // Do not modify interface
	parameter ADDR_W = 64,
	parameter INST_W = 32,
	parameter DATA_W = 64
)(
	input                   i_clk,
	input                   i_rst_n,
	input                   i_i_valid_inst, // from instruction memory
	input  [ INST_W-1 : 0 ] i_i_inst,       // from instruction memory
	input                   i_d_valid_data, // from data memory
	input  [ DATA_W-1 : 0 ] i_d_data,       // from data memory
	output                  o_i_valid_addr, // to instruction memory
	output [ ADDR_W-1 : 0 ] o_i_addr,       // to instruction memory
	output [ DATA_W-1 : 0 ] o_d_data,       // to data memory
	output [ ADDR_W-1 : 0 ] o_d_addr,       // to data memory
	output                  o_d_MemRead,    // to data memory
	output                  o_d_MemWrite,   // to data memory
	output                  o_finish
);

	// homework
	// wire and register
	reg o_i_valid_addr_r, o_i_valid_addr_w;
	reg [ADDR_W - 1:0] o_i_addr_r, o_i_addr_w;
	reg [DATA_W - 1:0] o_d_data_r, o_d_data_w;
	reg [ADDR_W - 1:0] o_d_addr_r, o_d_addr_w;
	reg o_d_MemRead_r, o_d_MemRead_w;
	reg o_d_MemWrite_r, o_d_MemWrite_w;
	reg o_finish_r, o_finish_w;
	reg [3:0] cs, ns;
	reg [12:0] pc;
	reg [DATA_W - 1:0] x_r[0:31];
	reg [DATA_W - 1:0] x_w[0:31];
	integer i;
	reg [4:0] rd_index;
	reg [12:0] pc_offset;
	// assignment
	assign o_i_valid_addr = o_i_valid_addr_r;
	assign o_i_addr = o_i_addr_r;
	assign o_d_data = o_d_data_r;
	assign o_d_addr = o_d_addr_r;
	assign o_d_MemRead = o_d_MemRead_r;
	assign o_d_MemWrite = o_d_MemWrite_r;
	assign o_finish = o_finish_r;
	// stage
	always @(*) begin
		case (cs)
			0: ns = 1;
			1: ns = 2;
			2: ns = 3;
			3: ns = 4;
			4: ns = 5;
			5: ns = 6;
			6: ns = 7;
			7: ns = 8;
			8: ns = 9;
			9: ns = 10;
			10: ns = 11;
			11: ns = 12;
			12: ns = 13;
			13: ns = 14;
			14: ns = 15;
			15: ns = 0;
		endcase
	end
	// combinational circuit
	always @(*) begin
		// start
		if (cs == 0) begin
			o_i_valid_addr_w = 1;
			o_i_addr_w = pc;
			o_d_MemRead_w = 0;
			o_d_MemWrite_w = 0;
			o_finish_w = 0;
		end
		// deal with instruction
		else if (i_i_valid_inst) begin
			// eof
			if (i_i_inst == 32'b11111111111111111111111111111111) begin
				o_finish_w = 1;
			end
			// store
			else if (i_i_inst[6:0] == 7'b0100011 && i_i_inst[14:12] == 3'b011) begin
				o_d_MemWrite_w = 1;
				o_d_addr_w = x_w[i_i_inst[19:15]] + {i_i_inst[31:25], i_i_inst[11:7]};
				o_d_data_w = x_w[i_i_inst[24:20]];
			end
			// addi
			else if (i_i_inst[6:0] == 7'b0010011 && i_i_inst[14:12] == 3'b000) begin
				x_w[i_i_inst[11:7]] = x_w[i_i_inst[19:15]] + i_i_inst[31:20];
			end
			// load
			else if (i_i_inst[6:0] == 7'b0000011 && i_i_inst[14:12] == 3'b011) begin
				rd_index = i_i_inst[11:7];
				o_d_MemRead_w = 1;
				o_d_addr_w = x_w[i_i_inst[19:15]] + i_i_inst[31:20];
			end
			// add
			else if (i_i_inst[6:0] == 7'b0110011 && i_i_inst[14:12] == 3'b000 && i_i_inst[31:25] == 7'b0000000) begin
				x_w[i_i_inst[11:7]] = x_w[i_i_inst[19:15]] + x_w[i_i_inst[24:20]];
			end
			// sub
			else if (i_i_inst[6:0] == 7'b0110011 && i_i_inst[14:12] == 3'b000 && i_i_inst[31:25] == 7'b0100000) begin
				x_w[i_i_inst[11:7]] = x_w[i_i_inst[19:15]] - x_w[i_i_inst[24:20]];
			end
			// and
			else if (i_i_inst[6:0] == 7'b0110011 && i_i_inst[14:12] == 3'b111 && i_i_inst[31:25] == 7'b0000000) begin
				x_w[i_i_inst[11:7]] = x_w[i_i_inst[19:15]] & x_w[i_i_inst[24:20]];
			end
			// or
			else if (i_i_inst[6:0] == 7'b0110011 && i_i_inst[14:12] == 3'b110 && i_i_inst[31:25] == 7'b0000000) begin
				x_w[i_i_inst[11:7]] = x_w[i_i_inst[19:15]] | x_w[i_i_inst[24:20]];
			end
			// xor
			else if (i_i_inst[6:0] == 7'b0110011 && i_i_inst[14:12] == 3'b100 && i_i_inst[31:25] == 7'b0000000) begin
				x_w[i_i_inst[11:7]] = (x_w[i_i_inst[19:15]] & ~x_w[i_i_inst[24:20]]) | (~x_w[i_i_inst[19:15]] & x_w[i_i_inst[24:20]]);
			end
			// andi
			else if (i_i_inst[6:0] == 7'b0010011 && i_i_inst[14:12] == 3'b111) begin
				x_w[i_i_inst[11:7]] = x_w[i_i_inst[19:15]] & i_i_inst[31:20];
			end
			// ori
			else if (i_i_inst[6:0] == 7'b0010011 && i_i_inst[14:12] == 3'b110) begin
				x_w[i_i_inst[11:7]] = x_w[i_i_inst[19:15]] | i_i_inst[31:20];
			end
			// xori
			else if (i_i_inst[6:0] == 7'b0010011 && i_i_inst[14:12] == 3'b100) begin
				x_w[i_i_inst[11:7]] = (x_w[i_i_inst[19:15]] & ~i_i_inst[31:20]) | (~x_w[i_i_inst[19:15]] & i_i_inst[31:20]);
			end
			// slli
			else if (i_i_inst[6:0] == 7'b0010011 && i_i_inst[14:12] == 3'b001 && i_i_inst[31:25] == 7'b0000000) begin
				x_w[i_i_inst[11:7]] = x_w[i_i_inst[19:15]] << i_i_inst[24:20];
			end
			// srli
			else if (i_i_inst[6:0] == 7'b0010011 && i_i_inst[14:12] == 3'b101 && i_i_inst[31:25] == 7'b0000000) begin
				x_w[i_i_inst[11:7]] = x_w[i_i_inst[19:15]] >> i_i_inst[24:20];
			end
			// bne
			else if (i_i_inst[6:0] == 7'b1100011 && i_i_inst[14:12] == 3'b001) begin
				if (x_w[i_i_inst[19:15]] != x_w[i_i_inst[24:20]]) begin
					pc_offset = {i_i_inst[31], i_i_inst[7], i_i_inst[30:25], i_i_inst[11:8], 1'b0};
				end
			end
			// beq
			else if (i_i_inst[6:0] == 7'b1100011 && i_i_inst[14:12] == 3'b000) begin
				if (x_w[i_i_inst[19:15]] == x_w[i_i_inst[24:20]]) begin
					pc_offset = {i_i_inst[31], i_i_inst[7], i_i_inst[30:25], i_i_inst[11:8], 1'b0};
				end
			end
		end
		// deal with pc
		else if (cs == 15) begin
			o_i_valid_addr_w = 0;
			pc = pc + $signed(pc_offset);
			if (pc_offset != 12'd4) begin
				pc_offset = 12'd4;
			end
			o_d_MemRead_w = 0;
			o_d_MemWrite_w = 0;
		end
		else begin
			o_i_valid_addr_w = 0;
			o_d_MemRead_w = 0;
			o_d_MemWrite_w = 0;
		end
		// receive loaded data
		if (i_d_valid_data) begin
			x_w[rd_index] = i_d_data;
		end
	end
	// sequential circuit
	always @(posedge i_clk or negedge i_rst_n) begin
		if (~i_rst_n) begin
			o_i_valid_addr_r <= 0;
			o_i_addr_r <= 0;
			o_d_data_r <= 0;
			o_d_addr_r <= 0;
			o_d_MemRead_r <= 0;
			o_d_MemWrite_r <= 0;
			o_finish_r <= 0;
			cs <= 0;
			pc <= 0;
			for (i = 0; i < 32; i = i + 1) begin
				x_r[i] <= 0;
				x_w[i] <= 0;
			end
			pc_offset <= 12'd4;
		end
		else begin
			o_i_valid_addr_r <= o_i_valid_addr_w;
			o_i_addr_r <= o_i_addr_w;
			o_d_data_r <= o_d_data_w;
			o_d_addr_r <= o_d_addr_w;
			o_d_MemRead_r <= o_d_MemRead_w;
			o_d_MemWrite_r <= o_d_MemWrite_w;
			o_finish_r <= o_finish_w;
			cs <= ns;
			for (i = 0; i < 32; i = i + 1) begin
				x_r[i] <= x_w[i];
			end
		end
	end

endmodule

Homework3/CPU/testbench.v
`timescale 1ns/1ps
`define CYCLE      10.0
`define HCYCLE     (`CYCLE/2)
`define RST_DELAY  5
`define MAX_CYCLE  10000

module test_cpu;

	parameter INST_W   = 32;
	parameter DATA_W   = 64;
	parameter ADDR_W   = 64;
	parameter MAX_INST = 16;

	wire                  i_clk;
	wire                  i_rst_n;
	wire [ INST_W-1 : 0 ] i_inst;
	wire                  i_valid_inst;
	wire [ DATA_W-1 : 0 ] read_data;
	wire                  d_valid_data;
	wire [ ADDR_W-1 : 0 ] i_addr;
	wire                  i_valid_addr;
	wire [ DATA_W-1 : 0 ] write_data;
	wire [ ADDR_W-1 : 0 ] write_addr;
	wire                  MemRead;
	wire                  MemWrite;
	wire                  Finish;

	reg clk;
	reg rst_n;
	reg [7:0] answer [0:1023];

	integer error, i;

	assign i_clk   = clk;
	assign i_rst_n = rst_n;

	initial begin
		$dumpfile("cpu.vcd");
		$dumpvars;
	end

	`ifdef T0
	initial $readmemb ("testcases/no_test_input.txt", u_inst_mem.mem);
	initial $readmemb ("testcases/no_test_output.txt", answer);
	`elsif T1
	initial $readmemb ("testcases/store_test_input.txt", u_inst_mem.mem);
	initial $readmemb ("testcases/store_test_output.txt", answer);
	`elsif T2
	initial $readmemb ("testcases/load_test_input.txt", u_inst_mem.mem);
	initial $readmemb ("testcases/load_test_output.txt", answer);
	`elsif T3
	initial $readmemb ("testcases/add_sub_test_input.txt", u_inst_mem.mem);
	initial $readmemb ("testcases/add_sub_test_output.txt", answer);
	`elsif T4
	initial $readmemb ("testcases/and_or_xor_test_input.txt", u_inst_mem.mem);
	initial $readmemb ("testcases/and_or_xor_test_output.txt", answer);
	`elsif T5
	initial $readmemb ("testcases/andi_ori_xori_test_input.txt", u_inst_mem.mem);
	initial $readmemb ("testcases/andi_ori_xori_test_output.txt", answer);
	`elsif T6
	initial $readmemb ("testcases/slli_srli_test_input.txt", u_inst_mem.mem);
	initial $readmemb ("testcases/slli_srli_test_output.txt", answer);
	`elsif T7
	initial $readmemb ("testcases/bne_beq_test_input.txt", u_inst_mem.mem);
	initial $readmemb ("testcases/bne_beq_test_output.txt", answer);
	`endif

	always # (`HCYCLE) clk = ~clk;

	initial begin
 		`ifdef T0
			$display("Eof test");
		`elsif T1
			$display("Store test");
		`elsif T2
			$display("Load test");
		`elsif T3
			$display("Add sub test");
		`elsif T4
			$display("And or xor test");
		`elsif T5
			$display("Andi ori xori test");
		`elsif T6
			$display("Slli srli test");
		`elsif T7
			$display("Bne beq test");
		`endif
		error = 0;
		clk   = 1'b1;
		rst_n = 1; # (               0.25 * `CYCLE);
		rst_n = 0; # ((`RST_DELAY - 0.25) * `CYCLE);
		rst_n = 1; # (         `MAX_CYCLE * `CYCLE);
		$finish;
	end

	always @(negedge i_clk) begin
		if (Finish) begin
			$display("Check memory");
			for (i = 0; i < 1024; i++) begin
				if (answer[i] !== u_data_mem.mem[i]) begin
					$display("Error!, at 0x%x, ans:%x, yours:%x", i, answer[i], u_data_mem.mem[i]);
					error = 1;
				end
			end
			if (!error) begin
				$display("Correct!");
			end
			$finish;
		end
	end

	cpu #(
		.INST_W(INST_W),
		.DATA_W(DATA_W),
		.ADDR_W(ADDR_W)
	) u_cpu (
		.i_clk(clk),
		.i_rst_n(i_rst_n),
		.i_i_valid_inst(i_valid_inst), // from instruction memory
		.i_i_inst(i_inst),             // from instruction memory
		.i_d_valid_data(d_valid_data), // from data memory
		.i_d_data(read_data),          // from data memory
		.o_i_valid_addr(i_valid_addr), // to instruction memory
		.o_i_addr(i_addr),             // to instruction memory
		.o_d_data(write_data),         // to data memory
		.o_d_addr(write_addr),         // to data memory
		.o_d_MemRead(MemRead),         // to data memory
		.o_d_MemWrite(MemWrite),       // to data memory
		.o_finish(Finish)
	);

	instruction_memory #(
		.ADDR_W(ADDR_W),
		.INST_W(INST_W),
		.MAX_INST(MAX_INST)
	) u_inst_mem (
		.i_clk(i_clk),
		.i_rst_n(i_rst_n),
		.i_valid(i_valid_addr),
		.i_addr(i_addr),
		.o_valid(i_valid_inst),
		.o_inst(i_inst)
	);

	data_memory #(
		.ADDR_W(ADDR_W),
		.DATA_W(DATA_W)
	) u_data_mem (
		.i_clk(i_clk),
		.i_rst_n(i_rst_n),
		.i_data(write_data),
		.i_addr(write_addr),
		.i_MemRead(MemRead),
		.i_MemWrite(MemWrite),
		.o_valid(d_valid_data),
		.o_data(read_data)
	);

endmodule

Homework3/CPU/cpu.vcd
$date
	Mon Feb 15 01:49:37 2021
$end
$version
	Icarus Verilog
$end
$timescale
	1ps
$end
$scope module test_cpu $end
$var wire 1 ! i_clk $end
$var wire 1 " i_rst_n $end
$var wire 64 # write_data [63:0] $end
$var wire 64 $ write_addr [63:0] $end
$var wire 64 % read_data [63:0] $end
$var wire 1 & i_valid_inst $end
$var wire 1 ' i_valid_addr $end
$var wire 32 ( i_inst [31:0] $end
$var wire 64 ) i_addr [63:0] $end
$var wire 1 * d_valid_data $end
$var wire 1 + MemWrite $end
$var wire 1 , MemRead $end
$var wire 1 - Finish $end
$var reg 1 . clk $end
$var reg 1 / rst_n $end
$var integer 32 0 error [31:0] $end
$var integer 32 1 i [31:0] $end
$scope module u_cpu $end
$var wire 1 . i_clk $end
$var wire 1 " i_rst_n $end
$var wire 64 2 o_d_addr [63:0] $end
$var wire 64 3 o_d_data [63:0] $end
$var wire 1 - o_finish $end
$var wire 64 4 o_i_addr [63:0] $end
$var wire 1 ' o_i_valid_addr $end
$var wire 1 + o_d_MemWrite $end
$var wire 1 , o_d_MemRead $end
$var wire 1 & i_i_valid_inst $end
$var wire 32 5 i_i_inst [31:0] $end
$var wire 1 * i_d_valid_data $end
$var wire 64 6 i_d_data [63:0] $end
$var reg 4 7 cs [3:0] $end
$var reg 4 8 ns [3:0] $end
$var reg 1 , o_d_MemRead_r $end
$var reg 1 9 o_d_MemRead_w $end
$var reg 1 + o_d_MemWrite_r $end
$var reg 1 : o_d_MemWrite_w $end
$var reg 64 ; o_d_addr_r [63:0] $end
$var reg 64 < o_d_addr_w [63:0] $end
$var reg 64 = o_d_data_r [63:0] $end
$var reg 64 > o_d_data_w [63:0] $end
$var reg 1 ? o_finish_r $end
$var reg 1 @ o_finish_w $end
$var reg 64 A o_i_addr_r [63:0] $end
$var reg 64 B o_i_addr_w [63:0] $end
$var reg 1 C o_i_valid_addr_r $end
$var reg 1 D o_i_valid_addr_w $end
$var reg 13 E pc [12:0] $end
$var reg 13 F pc_offset [12:0] $end
$var reg 5 G rd_index [4:0] $end
$var integer 32 H i [31:0] $end
$upscope $end
$scope module u_data_mem $end
$var wire 1 , i_MemRead $end
$var wire 1 + i_MemWrite $end
$var wire 64 I i_addr [63:0] $end
$var wire 1 ! i_clk $end
$var wire 64 J i_data [63:0] $end
$var wire 1 " i_rst_n $end
$var wire 1 K i_valid $end
$var wire 64 L o_data [63:0] $end
$var wire 1 * o_valid $end
$var reg 4 M cs [3:0] $end
$var reg 4 N ns [3:0] $end
$var reg 64 O o_data_r [63:0] $end
$var reg 64 P o_data_w [63:0] $end
$var reg 1 Q o_valid_r $end
$var reg 1 R o_valid_w $end
$var reg 1 S temp_MemRead $end
$var reg 1 T temp_MemRead_w $end
$var reg 1 U temp_MemWrite $end
$var reg 1 V temp_MemWrite_w $end
$var reg 64 W temp_addr [63:0] $end
$var reg 64 X temp_addr_w [63:0] $end
$var reg 64 Y temp_data [63:0] $end
$var reg 64 Z temp_data_w [63:0] $end
$var integer 32 [ i [31:0] $end
$upscope $end
$scope module u_inst_mem $end
$var wire 64 \ i_addr [63:0] $end
$var wire 1 ! i_clk $end
$var wire 1 " i_rst_n $end
$var wire 1 ' i_valid $end
$var wire 32 ] o_inst [31:0] $end
$var wire 1 & o_valid $end
$var reg 4 ^ cs [3:0] $end
$var reg 4 _ ns [3:0] $end
$var reg 32 ` o_inst_r [31:0] $end
$var reg 32 a o_inst_w [31:0] $end
$var reg 1 b o_valid_r $end
$var reg 1 c o_valid_w $end
$var reg 64 d temp_addr_r [63:0] $end
$var reg 64 e temp_addr_w [63:0] $end
$upscope $end
$upscope $end
$enddefinitions $end
#0
$dumpvars
bx e
bx d
0c
0b
b0 a
b0 `
bx _
bx ^
b0 ]
bx \
b10000000000 [
bx Z
bx Y
bx X
bx W
xV
xU
xT
xS
xR
xQ
bx P
bx O
bx N
bx M
bx L
xK
bx J
bx I
b100000 H
bx G
bx F
bx E
0D
xC
bx B
bx A
x@
x?
bx >
bx =
bx <
bx ;
0:
09
bx 8
bx 7
bx 6
b0 5
bx 4
bx 3
bx 2
bx 1
b0 0
1/
1.
x-
x,
x+
x*
bx )
b0 (
x'
0&
bx %
bx $
bx #
1"
1!
$end
#2500
b1 8
0K
0V
0T
b0 Z
b0 X
b0 N
b0 P
0R
0@
b0 B
1D
b0 e
b0 _
b100 F
b0 E
b0 7
0-
0?
0+
0,
b0 $
b0 2
b0 I
b0 ;
b0 #
b0 3
b0 J
b0 =
b0 )
b0 4
b0 \
b0 A
0'
0C
0U
0S
b0 Y
b0 W
b0 M
b0 %
b0 6
b0 L
b0 O
0*
0Q
b0 d
b0 ^
b100000 H
b10000000000 [
0"
0/
#5000
0!
0.
#10000
b100000 H
b10000000000 [
1!
1.
#15000
0!
0.
#20000
b100000 H
b10000000000 [
1!
1.
#25000
0!
0.
#30000
b100000 H
b10000000000 [
1!
1.
#35000
0!
0.
#40000
b100000 H
b10000000000 [
1!
1.
#45000
0!
0.
#50000
0D
b10 8
b1 _
b1 7
bx $
bx 2
bx I
bx ;
bx #
bx 3
bx J
bx =
1'
1C
b100000 H
b10000000000 [
1!
1.
1"
1/
#55000
0!
0.
#60000
b11 8
b10 _
b10 7
0'
0C
b1 ^
b100000 H
b10000000000 [
1!
1.
#65000
0!
0.
#70000
b100 8
b11 _
b11 7
b10 ^
b100000 H
b10000000000 [
1!
1.
#75000
0!
0.
#80000
b101 8
b100 _
b100 7
b11 ^
b100000 H
b10000000000 [
1!
1.
#85000
0!
0.
#90000
b110 8
b101 _
b101 7
b100 ^
b100000 H
b10000000000 [
1!
1.
#95000
0!
0.
#100000
b111 8
b0 _
b111101100000000001010010011 a
1c
b110 7
b101 ^
b100000 H
b10000000000 [
1!
1.
#105000
0!
0.
#110000
b1000 8
b0 a
0c
b111 7
b0 ^
b111101100000000001010010011 (
b111101100000000001010010011 5
b111101100000000001010010011 ]
b111101100000000001010010011 `
1&
1b
b100000 H
b10000000000 [
1!
1.
#115000
0!
0.
#120000
b1001 8
b1000 7
b0 (
b0 5
b0 ]
b0 `
0&
0b
b100000 H
b10000000000 [
1!
1.
#125000
0!
0.
#130000
b1010 8
b1001 7
b100000 H
b10000000000 [
1!
1.
#135000
0!
0.
#140000
b1011 8
b1010 7
b100000 H
b10000000000 [
1!
1.
#145000
0!
0.
#150000
b1100 8
b1011 7
b100000 H
b10000000000 [
1!
1.
#155000
0!
0.
#160000
b1101 8
b1100 7
b100000 H
b10000000000 [
1!
1.
#165000
0!
0.
#170000
b1110 8
b1101 7
b100000 H
b10000000000 [
1!
1.
#175000
0!
0.
#180000
b1111 8
b1110 7
b100000 H
b10000000000 [
1!
1.
#185000
0!
0.
#190000
b100 E
b0 8
b1111 7
b100000 H
b10000000000 [
1!
1.
#195000
0!
0.
#200000
b100 B
1D
b1 8
b0 7
b100000 H
b10000000000 [
1!
1.
#205000
0!
0.
#210000
0D
b10 8
b1 _
b100 e
b1 7
b100 )
b100 4
b100 \
b100 A
1'
1C
b100000 H
b10000000000 [
1!
1.
#215000
0!
0.
#220000
b11 8
b10 _
b10 7
0'
0C
b100 d
b1 ^
b100000 H
b10000000000 [
1!
1.
#225000
0!
0.
#230000
b100 8
b11 _
b11 7
b10 ^
b100000 H
b10000000000 [
1!
1.
#235000
0!
0.
#240000
b101 8
b100 _
b100 7
b11 ^
b100000 H
b10000000000 [
1!
1.
#245000
0!
0.
#250000
b110 8
b101 _
b101 7
b100 ^
b100000 H
b10000000000 [
1!
1.
#255000
0!
0.
#260000
b111 8
b0 _
b11100100000000000001100010011 a
1c
b110 7
b101 ^
b100000 H
b10000000000 [
1!
1.
#265000
0!
0.
#270000
b1000 8
b0 a
0c
b111 7
b0 ^
b11100100000000000001100010011 (
b11100100000000000001100010011 5
b11100100000000000001100010011 ]
b11100100000000000001100010011 `
1&
1b
b100000 H
b10000000000 [
1!
1.
#275000
0!
0.
#280000
b1001 8
b1000 7
b0 (
b0 5
b0 ]
b0 `
0&
0b
b100000 H
b10000000000 [
1!
1.
#285000
0!
0.
#290000
b1010 8
b1001 7
b100000 H
b10000000000 [
1!
1.
#295000
0!
0.
#300000
b1011 8
b1010 7
b100000 H
b10000000000 [
1!
1.
#305000
0!
0.
#310000
b1100 8
b1011 7
b100000 H
b10000000000 [
1!
1.
#315000
0!
0.
#320000
b1101 8
b1100 7
b100000 H
b10000000000 [
1!
1.
#325000
0!
0.
#330000
b1110 8
b1101 7
b100000 H
b10000000000 [
1!
1.
#335000
0!
0.
#340000
b1111 8
b1110 7
b100000 H
b10000000000 [
1!
1.
#345000
0!
0.
#350000
b1000 E
b0 8
b1111 7
b100000 H
b10000000000 [
1!
1.
#355000
0!
0.
#360000
b1000 B
1D
b1 8
b0 7
b100000 H
b10000000000 [
1!
1.
#365000
0!
0.
#370000
0D
b10 8
b1 _
b1000 e
b1 7
b1000 )
b1000 4
b1000 \
b1000 A
1'
1C
b100000 H
b10000000000 [
1!
1.
#375000
0!
0.
#380000
b11 8
b10 _
b10 7
0'
0C
b1000 d
b1 ^
b100000 H
b10000000000 [
1!
1.
#385000
0!
0.
#390000
b100 8
b11 _
b11 7
b10 ^
b100000 H
b10000000000 [
1!
1.
#395000
0!
0.
#400000
b101 8
b100 _
b100 7
b11 ^
b100000 H
b10000000000 [
1!
1.
#405000
0!
0.
#410000
b110 8
b101 _
b101 7
b100 ^
b100000 H
b10000000000 [
1!
1.
#415000
0!
0.
#420000
b111 8
b0 _
b111101100000000001110010011 a
1c
b110 7
b101 ^
b100000 H
b10000000000 [
1!
1.
#425000
0!
0.
#430000
b1000 8
b0 a
0c
b111 7
b0 ^
b111101100000000001110010011 (
b111101100000000001110010011 5
b111101100000000001110010011 ]
b111101100000000001110010011 `
1&
1b
b100000 H
b10000000000 [
1!
1.
#435000
0!
0.
#440000
b1001 8
b1000 7
b0 (
b0 5
b0 ]
b0 `
0&
0b
b100000 H
b10000000000 [
1!
1.
#445000
0!
0.
#450000
b1010 8
b1001 7
b100000 H
b10000000000 [
1!
1.
#455000
0!
0.
#460000
b1011 8
b1010 7
b100000 H
b10000000000 [
1!
1.
#465000
0!
0.
#470000
b1100 8
b1011 7
b100000 H
b10000000000 [
1!
1.
#475000
0!
0.
#480000
b1101 8
b1100 7
b100000 H
b10000000000 [
1!
1.
#485000
0!
0.
#490000
b1110 8
b1101 7
b100000 H
b10000000000 [
1!
1.
#495000
0!
0.
#500000
b1111 8
b1110 7
b100000 H
b10000000000 [
1!
1.
#505000
0!
0.
#510000
b1100 E
b0 8
b1111 7
b100000 H
b10000000000 [
1!
1.
#515000
0!
0.
#520000
b1100 B
1D
b1 8
b0 7
b100000 H
b10000000000 [
1!
1.
#525000
0!
0.
#530000
0D
b10 8
b1 _
b1100 e
b1 7
b1100 )
b1100 4
b1100 \
b1100 A
1'
1C
b100000 H
b10000000000 [
1!
1.
#535000
0!
0.
#540000
b11 8
b10 _
b10 7
0'
0C
b1100 d
b1 ^
b100000 H
b10000000000 [
1!
1.
#545000
0!
0.
#550000
b100 8
b11 _
b11 7
b10 ^
b100000 H
b10000000000 [
1!
1.
#555000
0!
0.
#560000
b101 8
b100 _
b100 7
b11 ^
b100000 H
b10000000000 [
1!
1.
#565000
0!
0.
#570000
b110 8
b101 _
b101 7
b100 ^
b100000 H
b10000000000 [
1!
1.
#575000
0!
0.
#580000
b111 8
b0 _
b11000101001011001100011 a
1c
b110 7
b101 ^
b100000 H
b10000000000 [
1!
1.
#585000
0!
0.
#590000
b1000 8
b0 a
0c
b1100 F
b111 7
b0 ^
b11000101001011001100011 (
b11000101001011001100011 5
b11000101001011001100011 ]
b11000101001011001100011 `
1&
1b
b100000 H
b10000000000 [
1!
1.
#595000
0!
0.
#600000
b1001 8
b1000 7
b0 (
b0 5
b0 ]
b0 `
0&
0b
b100000 H
b10000000000 [
1!
1.
#605000
0!
0.
#610000
b1010 8
b1001 7
b100000 H
b10000000000 [
1!
1.
#615000
0!
0.
#620000
b1011 8
b1010 7
b100000 H
b10000000000 [
1!
1.
#625000
0!
0.
#630000
b1100 8
b1011 7
b100000 H
b10000000000 [
1!
1.
#635000
0!
0.
#640000
b1101 8
b1100 7
b100000 H
b10000000000 [
1!
1.
#645000
0!
0.
#650000
b1110 8
b1101 7
b100000 H
b10000000000 [
1!
1.
#655000
0!
0.
#660000
b1111 8
b1110 7
b100000 H
b10000000000 [
1!
1.
#665000
0!
0.
#670000
b100 F
b11000 E
b0 8
b1111 7
b100000 H
b10000000000 [
1!
1.
#675000
0!
0.
#680000
b11000 B
1D
b1 8
b0 7
b100000 H
b10000000000 [
1!
1.
#685000
0!
0.
#690000
0D
b10 8
b1 _
b11000 e
b1 7
b11000 )
b11000 4
b11000 \
b11000 A
1'
1C
b100000 H
b10000000000 [
1!
1.
#695000
0!
0.
