Homework3/FPU/codes/fpu.v
module fpu #(
	parameter DATA_WIDTH = 32,
	parameter INST_WIDTH = 1
)(
	input                   i_clk,
	input                   i_rst_n,
	input  [DATA_WIDTH-1:0] i_data_a,
	input  [DATA_WIDTH-1:0] i_data_b,
	input  [INST_WIDTH-1:0] i_inst,
	input                   i_valid,
	output [DATA_WIDTH-1:0] o_data,
	output                  o_valid
);

	// homework
	// wire and register
	reg [DATA_WIDTH - 1:0] o_data_r, o_data_w;
	reg o_overflow_w;
	reg o_valid_r, o_valid_w;
	reg [7:0] exponent_a_w, exponent_b_w;
	reg [7:0] o_exponent_w;
	reg [23:0] fraction_a_w, fraction_b_w;
	reg [23:0] o_fraction_w;
	reg [46:0] o_mul_temp;
	reg o_sign_w;
	wire int;
	reg R, S;
	integer i;
	// assignment
	assign o_data = o_data_r;
	assign o_valid = o_valid_r;
	assign int = 1;
	// combinational circuit
	always @(*) begin
		if (i_valid) begin
			exponent_a_w = i_data_a[30:23];
			exponent_b_w = i_data_b[30:23];
			fraction_a_w = {int, i_data_a[22:0]};
			fraction_b_w = {int, i_data_b[22:0]};
			case (i_inst)
				// add
				1'd0: begin
					// shift number with smaller exponent right
					if (exponent_a_w > exponent_b_w) begin
						S = 0;
						for (i = 0; i < exponent_a_w - exponent_b_w - 1; i = i + 1) begin
							if (fraction_b_w[i] == 1) begin
								S = 1;
							end
						end
						R = fraction_b_w[i];
						fraction_b_w = fraction_b_w >> (exponent_a_w - exponent_b_w);
						exponent_b_w = exponent_a_w;
						o_exponent_w = exponent_a_w;
					end
					else if (exponent_a_w < exponent_b_w) begin
						S = 0;
						for (i = 0; i < exponent_b_w - exponent_a_w - 1; i = i + 1) begin
							if (fraction_a_w[i] == 1) begin
								S = 1;
							end
						end
						R = fraction_a_w[i];
						fraction_a_w = fraction_a_w >> (exponent_b_w - exponent_a_w);
						exponent_a_w = exponent_b_w;
						o_exponent_w = exponent_b_w;
					end
					else begin
						R = 0;
						S = 0;
						o_exponent_w = exponent_b_w;
					end
					// add or sub
					if (~i_data_a[DATA_WIDTH - 1] && ~i_data_b[DATA_WIDTH - 1]) begin
						{o_overflow_w, o_fraction_w} = fraction_a_w + fraction_b_w;
						o_sign_w = 0;
					end
					else if (i_data_a[DATA_WIDTH - 1] && i_data_b[DATA_WIDTH - 1]) begin
						{o_overflow_w, o_fraction_w} = fraction_a_w + fraction_b_w;
						o_sign_w = 1;
					end
					else if (~i_data_a[DATA_WIDTH - 1] && i_data_b[DATA_WIDTH - 1]) begin
						if (fraction_a_w > fraction_b_w) begin
							{o_overflow_w, o_fraction_w} = fraction_a_w - fraction_b_w;
							o_sign_w = 0;
						end
						else begin
							{o_overflow_w, o_fraction_w} = fraction_b_w - fraction_a_w;
							o_sign_w = 1;
						end
					end
					else begin
						if (fraction_a_w < fraction_b_w) begin
							{o_overflow_w, o_fraction_w} = fraction_b_w - fraction_a_w;
							o_sign_w = 0;
						end
						else begin
							{o_overflow_w, o_fraction_w} = fraction_a_w - fraction_b_w;
							o_sign_w = 1;
						end
					end
					// normalize
					if (o_overflow_w) begin
						o_exponent_w = o_exponent_w + 8'b1;
						if (R || S) begin
							S = 1;
						end
						R = o_fraction_w[0];
						o_fraction_w = o_fraction_w >> 1;
					end
					// rounding to the nearest even
					if (R == 0 && S == 0) begin
						{o_overflow_w, o_fraction_w} = o_fraction_w;
					end
					else if (R == 0 && S == 1) begin
						{o_overflow_w, o_fraction_w} = o_fraction_w;
					end
					else if (R == 1 && S == 1) begin
						if (~i_data_a[DATA_WIDTH - 1] && ~i_data_b[DATA_WIDTH - 1]) begin
							{o_overflow_w, o_fraction_w} = o_fraction_w + 24'b1;
						end
						else begin
							{o_overflow_w, o_fraction_w} = o_fraction_w - 24'b1;
						end
					end
					else if (R == 1 && S == 0) begin
						if (o_fraction_w[0]) begin
							if (~i_data_a[DATA_WIDTH - 1] && ~i_data_b[DATA_WIDTH - 1]) begin
								{o_overflow_w, o_fraction_w} = o_fraction_w + 24'b1;
							end
							else begin
								{o_overflow_w, o_fraction_w} = o_fraction_w - 24'b1;
							end
						end
						else begin
							{o_overflow_w, o_fraction_w} = o_fraction_w;
						end
					end
					// re-normalize
					if (o_overflow_w) begin
						o_exponent_w = o_exponent_w + 8'b1;
						o_fraction_w = o_fraction_w >> 1;
					end
					// combine
					o_data_w = {o_sign_w, o_exponent_w, o_fraction_w[22:0]};
					o_valid_w = 1;
				end
				// mul
				1'd1: begin
					// add exponents
					o_exponent_w = exponent_a_w + exponent_b_w - 8'd127;
					// mul
					{o_overflow_w, o_mul_temp} = fraction_a_w * fraction_b_w;
					S = 0;
					for (i = 0; i < 22; i = i + 1) begin
						if (o_mul_temp[i] == 1) begin
							S = 1;
						end
					end
					R = o_mul_temp[22];
					o_fraction_w = o_mul_temp[46:23];
					// sign
					if (i_data_a[DATA_WIDTH - 1] == i_data_b[DATA_WIDTH - 1]) begin
						o_sign_w = 0;
					end
					else begin
						o_sign_w = 1;
					end
					// normalize
					if (o_overflow_w) begin
						o_exponent_w = o_exponent_w + 8'b1;
						if (R || S) begin
							S = 1;
						end
						R = o_fraction_w[0];
						o_fraction_w = o_fraction_w >> 1;
					end
					// rounding to the nearest even
					if (R == 0 && S == 0) begin
						{o_overflow_w, o_fraction_w} = o_fraction_w;
					end
					else if (R == 0 && S == 1) begin
						{o_overflow_w, o_fraction_w} = o_fraction_w;
					end
					else if (R == 1 && S == 1) begin
						if (~i_data_a[DATA_WIDTH - 1] && ~i_data_b[DATA_WIDTH - 1]) begin
							{o_overflow_w, o_fraction_w} = o_fraction_w + 24'b1;
						end
						else begin
							{o_overflow_w, o_fraction_w} = o_fraction_w - 24'b1;
						end
					end
					else if (R == 1 && S == 0) begin
						if (o_fraction_w[0]) begin
							if (~i_data_a[DATA_WIDTH - 1] && ~i_data_b[DATA_WIDTH - 1]) begin
								{o_overflow_w, o_fraction_w} = o_fraction_w + 24'b1;
							end
							else begin
								{o_overflow_w, o_fraction_w} = o_fraction_w - 24'b1;
							end
						end
						else begin
							{o_overflow_w, o_fraction_w} = o_fraction_w;
						end
					end
					// re-normalize
					if (o_overflow_w) begin
						o_exponent_w = o_exponent_w + 8'b1;
						o_fraction_w = o_fraction_w >> 1;
					end
					// combine
					o_data_w = {o_sign_w, o_exponent_w, o_fraction_w[22:0]};
					o_valid_w = 1;
				end
				// default
				default: begin
					o_data_w = 0;
					o_valid_w = 1;
				end
			endcase
		end
		else begin
			o_data_w = 0;
			o_valid_w = 0;
		end
	end
	// sequential circuit
	always @(posedge i_clk or negedge i_rst_n) begin
		if (~i_rst_n) begin
			o_data_r <= 0;
			o_valid_r <= 0;
		end
		else begin
			o_data_r <= o_data_w;
			o_valid_r <= o_valid_w;
		end
	end

endmodule

Homework3/FPU/testbench.v
`timescale 1ns/1ps
`define CYCLE      10.0
`define HCYCLE     (`CYCLE/2)
`define RST_DELAY  5
`define MAX_CYCLE  1000

module test_fpu;

	parameter DATA_WIDTH  = 32;
	parameter INST_WIDTH  = 1;
	parameter NUM_OF_INST = 2;
	parameter NUM_OF_TEST = 10;

	initial begin
		$dumpfile("fpu.vcd");
		$dumpvars;
	end

	wire                  clk;
	wire                  rst_n;
	wire                  ivalid;
	wire [DATA_WIDTH-1:0] idata_a;
	wire [DATA_WIDTH-1:0] idata_b;
	wire [INST_WIDTH-1:0] inst;
	wire                  ovalid;
	wire [DATA_WIDTH-1:0] odata;

	fpu #(
		.DATA_WIDTH(DATA_WIDTH),
		.INST_WIDTH(INST_WIDTH)
	) u_fpu (
		.i_clk(clk),
		.i_rst_n(rst_n),
		.i_data_a(idata_a),
		.i_data_b(idata_b),
		.i_inst(inst),
		.i_valid(ivalid),
		.o_data(odata),
		.o_valid(ovalid)
	);

	fpu_test #(
		.DATA_WIDTH(DATA_WIDTH),
		.INST_WIDTH(INST_WIDTH),
		.NUM_OF_INST(NUM_OF_INST),
		.NUM_OF_TEST(NUM_OF_TEST)
	) u_fpu_test (
		.i_clk(clk),
		.i_rst_n(rst_n),
		.i_data(odata),
		.i_valid(ovalid),
		.o_data_a(idata_a),
		.o_data_b(idata_b),
		.o_inst(inst),
		.o_valid(ivalid)
	);

	Clkgen u_clk (
		.clk(clk),
		.rst_n(rst_n)
	);

endmodule

module Clkgen (
	output reg clk,
	output reg rst_n
);
	always # (`HCYCLE) clk = ~clk;

	initial begin
		clk = 1'b1;
		rst_n = 1; # (               0.25 * `CYCLE);
		rst_n = 0; # ((`RST_DELAY - 0.25) * `CYCLE);
		$display("==========================================================================================");
		$display("Start testing");
		$display("==========================================================================================");
		rst_n = 1; # (         `MAX_CYCLE * `CYCLE);
		$finish;
	end
endmodule


module fpu_test #(
	parameter DATA_WIDTH  = 32,
	parameter INST_WIDTH  = 1,
	parameter NUM_OF_INST = 2,
	parameter NUM_OF_TEST = 10
)(
	input                       i_clk,
	input                       i_rst_n,
	input      [DATA_WIDTH-1:0] i_data,
	input                       i_valid,
	output reg [DATA_WIDTH-1:0] o_data_a,
	output reg [DATA_WIDTH-1:0] o_data_b,
	output reg [INST_WIDTH-1:0] o_inst,
	output reg                  o_valid
);

	reg             [1:0] ns, cs;
	reg                   test_start [0:NUM_OF_INST-1];
	wire                  test_done  [0:NUM_OF_INST-1];
	wire [DATA_WIDTH-1:0] test_dataA [0:NUM_OF_INST-1];
	wire [DATA_WIDTH-1:0] test_dataB [0:NUM_OF_INST-1];
	wire [INST_WIDTH-1:0] test_inst  [0:NUM_OF_INST-1];
	wire                  test_valid [0:NUM_OF_INST-1];
	integer total_error = 0;

	genvar i;
	generate
		for(i = 0; i < NUM_OF_INST; i=i+1) begin: test_unit
			test_interface #(
				.DATA_WIDTH(DATA_WIDTH),
				.INST_WIDTH(INST_WIDTH),
				.NUM_OF_TEST(NUM_OF_TEST)
			) inst (
				.i_clk(i_clk),
				.i_rst_n(i_rst_n),
				.i_start(test_start[i]),
				.i_data(i_data),
				.i_valid(i_valid),
				.o_data_a(test_dataA[i]),
				.o_data_b(test_dataB[i]),
				.o_inst(test_inst[i]),
				.o_valid(test_valid[i]),
				.o_done(test_done[i])
			);
		end
	endgenerate

	initial $readmemb ("./testcases/test00_input.txt",  test_unit[0].inst.input_array);
	initial $readmemb ("./testcases/test00_output.txt", test_unit[0].inst.output_array);
	initial $readmemb ("./testcases/test01_input.txt",  test_unit[1].inst.input_array);
	initial $readmemb ("./testcases/test01_output.txt", test_unit[1].inst.output_array);

	localparam
		Idle   = 0,
		Test00 = 1,
		Test01 = 2,
		End    = 3;

	always @(*) begin
		ns      = cs;
		o_valid = 0;
		case (cs)
			Idle: begin
				ns = Test00;
			end
			Test00: begin
				test_start[0] = 1'b1;
				o_data_a      = test_dataA[0];
				o_data_b      = test_dataB[0];
				o_inst        = test_inst[0];
				o_valid       = test_valid[0];
				if (test_done[0]) begin
					ns = Test01;
					total_error = total_error + test_unit[0].inst.error;
					$display("Finish add test.");
					$display("==========================================================================================");
				end
			end
			Test01: begin
				test_start[1] = 1'b1;
				o_data_a      = test_dataA[1];
				o_data_b      = test_dataB[1];
				o_inst        = test_inst[1];
				o_valid       = test_valid[1];
				if (test_done[1]) begin
					ns = End;
					total_error = total_error + test_unit[1].inst.error;
					$display("Finish mul test.");
					$display("==========================================================================================");
				end
			end
			End: begin
				ns = End;
				$display("Finish all tests.");
				$display("Score: %.1f/20.0", (20-total_error));
				$finish;
			end
		endcase
	end

	always @(negedge i_clk or negedge i_rst_n) begin
		if (~i_rst_n) begin
			cs <= Idle;
		end else begin
			cs <= ns;
		end
	end

endmodule

module test_interface #(
	parameter DATA_WIDTH  = 32,
	parameter INST_WIDTH  = 1,
	parameter NUM_OF_TEST = 10
)(
	input                   i_clk,
	input                   i_rst_n,
	input                   i_start,
	input  [DATA_WIDTH-1:0] i_data,
	input                   i_valid,
	output [DATA_WIDTH-1:0] o_data_a,
	output [DATA_WIDTH-1:0] o_data_b,
	output [INST_WIDTH-1:0] o_inst,
	output                  o_valid,
	output                  o_done
);

	reg [2*DATA_WIDTH+INST_WIDTH-1:0] input_array  [0:NUM_OF_TEST-1];
	reg [2*DATA_WIDTH+INST_WIDTH-1:0] output_array [0:NUM_OF_TEST-1];

	localparam
		Idle_  = 0,
		Read   = 1,
		Write  = 2,
		Done   = 3,
		Finish = 4;

	reg                   o_valid_w, o_valid_r;
	reg  [DATA_WIDTH-1:0] o_data_a_w, o_data_a_r;
	reg  [DATA_WIDTH-1:0] o_data_b_w, o_data_b_r;
	reg  [           2:0] cs_, ns_;
	reg  [           3:0] idx_w, idx_r;

	wire [DATA_WIDTH-1:0] input_A, input_B, output_data;
	wire                  test_finish;

	integer error;

	assign test_finish     = (idx_r == NUM_OF_TEST-1);
	assign input_A         = input_array[idx_r][DATA_WIDTH-1:0];
	assign input_B         = input_array[idx_r][2*DATA_WIDTH-1:DATA_WIDTH];
	assign output_data     = output_array[idx_r][DATA_WIDTH-1:0];

	assign o_data_a        = o_data_a_r;
	assign o_data_b        = o_data_b_r;
	assign o_inst          = input_array[idx_r][2*DATA_WIDTH+INST_WIDTH-1:2*DATA_WIDTH];
	assign o_valid         = o_valid_r;
	assign o_done          = (cs_ == Finish);

	always @(*) begin
		case (cs_)
			Idle_   : ns_ = (i_start) ? Read : Idle_;
			Read    : ns_ = Write;
			Write   : ns_ = (i_valid) ? (test_finish ? Done : Read) : Write;
			Done    : ns_ = Finish;
			Finish  : ns_ = Finish;
			default : ns_ = Idle_;
		endcase
	end

	always @(*) begin
		idx_w = idx_r;
		o_valid_w  = 0;
		o_data_a_w = 0;
		o_data_b_w = 0;
		case (cs_)
			Read: begin
				o_valid_w = 1;
				o_data_a_w = input_array[idx_r][DATA_WIDTH-1:0];
				o_data_b_w = input_array[idx_r][2*DATA_WIDTH-1:DATA_WIDTH];
			end
			Write: begin
				idx_w = (i_valid && !test_finish) ? idx_r+1 : idx_r;
			end
		endcase
	end

	always @(negedge i_clk) begin
		if (cs_ == Idle_) begin
			error = 0;
		end else if (cs_ == Write && i_valid) begin
			if (i_data !== output_data) begin
				$display("Test #%d: Error! A=0x%x, B=0x%x, yours=0x%x, answer=0x%x",
					idx_r, input_A, input_B, i_data, output_data);
				error = error+1;
			end else begin
				$display("Test #%d: Correct!", idx_r);
			end
		end
		else if (cs_ == Done) begin
			if (error == 0) begin
				$display("ALL PASS!");
			end else begin
				$display("#Errors: %d", error);
			end
		end
	end

	always @(negedge i_clk or negedge i_rst_n) begin
		if (~i_rst_n) begin
			cs_        <= Idle_;
			idx_r      <= 0;
			o_valid_r  <= 0;
			o_data_a_r <= 0;
			o_data_b_r <= 0;
		end else begin
			cs_        <= ns_;
			idx_r      <= idx_w;
			o_valid_r  <= o_valid_w;
			o_data_a_r <= o_data_a_w;
			o_data_b_r <= o_data_b_w;
		end
	end

endmodule

Homework3/FPU/fpu.vcd
$date
	Fri Feb 12 21:01:46 2021
$end
$version
	Icarus Verilog
$end
$timescale
	1ps
$end
$scope module test_fpu $end
$var wire 1 ! rst_n $end
$var wire 1 " ovalid $end
$var wire 32 # odata [31:0] $end
$var wire 1 $ ivalid $end
$var wire 1 % inst $end
$var wire 32 & idata_b [31:0] $end
$var wire 32 ' idata_a [31:0] $end
$var wire 1 ( clk $end
$scope module u_clk $end
$var reg 1 ( clk $end
$var reg 1 ! rst_n $end
$upscope $end
$scope module u_fpu $end
$var wire 1 ( i_clk $end
$var wire 1 ! i_rst_n $end
$var wire 1 ) int $end
$var wire 32 * o_data [31:0] $end
$var wire 1 " o_valid $end
$var wire 1 $ i_valid $end
$var wire 1 % i_inst $end
$var wire 32 + i_data_b [31:0] $end
$var wire 32 , i_data_a [31:0] $end
$var reg 1 - R $end
$var reg 1 . S $end
$var reg 8 / exponent_a_w [7:0] $end
$var reg 8 0 exponent_b_w [7:0] $end
$var reg 24 1 fraction_a_w [23:0] $end
$var reg 24 2 fraction_b_w [23:0] $end
$var reg 32 3 o_data_r [31:0] $end
$var reg 32 4 o_data_w [31:0] $end
$var reg 8 5 o_exponent_w [7:0] $end
$var reg 24 6 o_fraction_w [23:0] $end
$var reg 47 7 o_mul_temp [46:0] $end
$var reg 1 8 o_overflow_w $end
$var reg 1 9 o_sign_w $end
$var reg 1 : o_valid_r $end
$var reg 1 ; o_valid_w $end
$var integer 32 < i [31:0] $end
$upscope $end
$scope module u_fpu_test $end
$var wire 1 ( i_clk $end
$var wire 32 = i_data [31:0] $end
$var wire 1 ! i_rst_n $end
$var wire 1 " i_valid $end
$var reg 2 > cs [1:0] $end
$var reg 2 ? ns [1:0] $end
$var reg 32 @ o_data_a [31:0] $end
$var reg 32 A o_data_b [31:0] $end
$var reg 1 % o_inst $end
$var reg 1 $ o_valid $end
$var integer 32 B total_error [31:0] $end
$scope begin test_unit[0] $end
$scope module inst $end
$var wire 1 ( i_clk $end
$var wire 32 C i_data [31:0] $end
$var wire 1 ! i_rst_n $end
$var wire 1 D i_start $end
$var wire 1 " i_valid $end
$var wire 32 E o_data_a [31:0] $end
$var wire 32 F o_data_b [31:0] $end
$var wire 1 G o_valid $end
$var wire 1 H test_finish $end
$var wire 32 I output_data [31:0] $end
$var wire 1 J o_inst $end
$var wire 1 K o_done $end
$var wire 32 L input_B [31:0] $end
$var wire 32 M input_A [31:0] $end
$var reg 3 N cs_ [2:0] $end
$var reg 4 O idx_r [3:0] $end
$var reg 4 P idx_w [3:0] $end
$var reg 3 Q ns_ [2:0] $end
$var reg 32 R o_data_a_r [31:0] $end
$var reg 32 S o_data_a_w [31:0] $end
$var reg 32 T o_data_b_r [31:0] $end
$var reg 32 U o_data_b_w [31:0] $end
$var reg 1 V o_valid_r $end
$var reg 1 W o_valid_w $end
$var integer 32 X error [31:0] $end
$upscope $end
$upscope $end
$scope begin test_unit[1] $end
$scope module inst $end
$var wire 1 ( i_clk $end
$var wire 32 Y i_data [31:0] $end
$var wire 1 ! i_rst_n $end
$var wire 1 Z i_start $end
$var wire 1 " i_valid $end
$var wire 32 [ o_data_a [31:0] $end
$var wire 32 \ o_data_b [31:0] $end
$var wire 1 ] o_valid $end
$var wire 1 ^ test_finish $end
$var wire 32 _ output_data [31:0] $end
$var wire 1 ` o_inst $end
$var wire 1 a o_done $end
$var wire 32 b input_B [31:0] $end
$var wire 32 c input_A [31:0] $end
$var reg 3 d cs_ [2:0] $end
$var reg 4 e idx_r [3:0] $end
$var reg 4 f idx_w [3:0] $end
$var reg 3 g ns_ [2:0] $end
$var reg 32 h o_data_a_r [31:0] $end
$var reg 32 i o_data_a_w [31:0] $end
$var reg 32 j o_data_b_r [31:0] $end
$var reg 32 k o_data_b_w [31:0] $end
$var reg 1 l o_valid_r $end
$var reg 1 m o_valid_w $end
$var integer 32 n error [31:0] $end
$upscope $end
$upscope $end
$upscope $end
$upscope $end
$enddefinitions $end
#0
$dumpvars
bx n
0m
xl
b0 k
bx j
b0 i
bx h
b0 g
bx f
bx e
bx d
bx c
bx b
xa
x`
bx _
x^
x]
bx \
bx [
xZ
b0 Y
bx X
0W
xV
b0 U
bx T
b0 S
bx R
b0 Q
bx P
bx O
bx N
bx M
bx L
xK
xJ
bx I
xH
xG
bx F
bx E
xD
b0 C
b0 B
bx A
bx @
bx ?
bx >
b0 =
bx <
0;
0:
x9
x8
bx 7
bx 6
bx 5
b0 4
b0 3
bx 2
bx 1
bx 0
bx /
x.
x-
bx ,
bx +
b0 *
1)
1(
bx '
bx &
x%
0$
b0 #
0"
1!
$end
#2500
b111111100000000000000000000000 M
b111111100000000000000000000000 L
b1000000000000000000000000000000 I
0J
b0 P
b0x Q
b111111101100000000000000000000 c
b111111000000000000000000000000 b
b111111001100000000000000000000 _
1`
b0 f
b0x g
b1 ?
b0 F
b0 T
b0 E
b0 R
0G
0V
0H
b0 O
0K
b0 N
b0 \
b0 j
b0 [
b0 h
0]
0l
0^
b0 e
0a
b0 d
b0 >
0!
#5000
b1 ?
b0 X
b0 n
0(
#10000
1(
#15000
0(
#20000
1(
#25000
0(
#30000
1(
#35000
0(
#40000
1(
#45000
0(
#50000
1(
1!
#55000
b0 Q
b0 g
0%
b0 &
b0 +
b0 A
b0 '
b0 ,
b0 @
1D
b0x N
b0x d
b1 >
0(
#60000
1(
#65000
b0x g
b1 Q
b0 d
b0 N
0(
#70000
1(
#75000
b111111100000000000000000000000 U
b111111100000000000000000000000 S
1W
b10 Q
b0 g
b1 N
b0x d
0(
#80000
1(
#85000
1;
b1000000000000000000000000000000 4
09
08
b0 6
b10000000 5
0.
0-
b100000000000000000000000 2
b100000000000000000000000 1
b1111111 0
b1111111 /
b0x g
1$
b111111100000000000000000000000 &
b111111100000000000000000000000 +
b111111100000000000000000000000 A
b111111100000000000000000000000 '
b111111100000000000000000000000 ,
b111111100000000000000000000000 @
b0 U
b0 S
0W
b0 d
b111111100000000000000000000000 F
b111111100000000000000000000000 T
b111111100000000000000000000000 E
b111111100000000000000000000000 R
1G
1V
b10 N
0(
#90000
b1 P
b1 Q
1"
1:
b1000000000000000000000000000000 #
b1000000000000000000000000000000 *
b1000000000000000000000000000000 =
b1000000000000000000000000000000 C
b1000000000000000000000000000000 Y
b1000000000000000000000000000000 3
1(
#95000
0;
b0 4
b0 &
b0 +
b0 A
b0 '
b0 ,
b0 @
0$
b111111101100000000000000000000 M
b111111000000000000000000000000 L
b111111111100000000000000000000 I
b111111000000000000000000000000 U
b111111101100000000000000000000 S
1W
b10 Q
b0 g
b0 F
b0 T
b0 E
b0 R
0G
0V
b1 O
b1 N
b0x d
0(
#100000
b111111000000000000000000000000 U
b111111101100000000000000000000 S
1W
0"
0:
b0 #
b0 *
b0 =
b0 C
b0 Y
b0 3
1(
#105000
1;
b111111111100000000000000000000 4
b111100000000000000000000 6
b1111111 5
b10000000000000000000000 2
b0 <
b101100000000000000000000 1
b1111111 0
b0x g
1$
b111111000000000000000000000000 &
b111111000000000000000000000000 +
b111111000000000000000000000000 A
b111111101100000000000000000000 '
b111111101100000000000000000000 ,
b111111101100000000000000000000 @
b0 U
b0 S
0W
b0 d
b111111000000000000000000000000 F
b111111000000000000000000000000 T
b111111101100000000000000000000 E
b111111101100000000000000000000 R
1G
1V
b10 N
0(
#110000
b10 P
b1 Q
1"
1:
b111111111100000000000000000000 #
b111111111100000000000000000000 *
b111111111100000000000000000000 =
b111111111100000000000000000000 C
b111111111100000000000000000000 Y
b111111111100000000000000000000 3
1(
#115000
0;
b0 4
b0 &
b0 +
b0 A
b0 '
b0 ,
b0 @
0$
b111111101101001111110111110100 M
b111101000000001010110111110101 L
b111111101110010000001101100100 I
b111101000000001010110111110101 U
b111111101101001111110111110100 S
1W
b10 Q
b0 g
b0 F
b0 T
b0 E
b0 R
0G
0V
b10 O
b1 N
b0x d
0(
#120000
b111101000000001010110111110101 U
b111111101101001111110111110100 S
1W
0"
0:
b0 #
b0 *
b0 =
b0 C
b0 Y
b0 3
1(
#125000
1;
b111111101110010000001101100100 4
b101110010000001101100100 6
1-
b100 <
1.
b1000000010101101111 2
b101101001111110111110100 1
b1111111 0
b0x g
1$
b111101000000001010110111110101 &
b111101000000001010110111110101 +
b111101000000001010110111110101 A
b111111101101001111110111110100 '
b111111101101001111110111110100 ,
b111111101101001111110111110100 @
b0 U
b0 S
0W
b0 d
b111101000000001010110111110101 F
b111101000000001010110111110101 T
b111111101101001111110111110100 E
b111111101101001111110111110100 R
1G
1V
b10 N
0(
#130000
b11 P
b1 Q
1"
1:
b111111101110010000001101100100 #
b111111101110010000001101100100 *
b111111101110010000001101100100 =
b111111101110010000001101100100 C
b111111101110010000001101100100 Y
b111111101110010000001101100100 3
1(
#135000
0;
b0 4
b0 &
b0 +
b0 A
b0 '
b0 ,
b0 @
0$
b111011010011011110001100100010 M
b111111101101001111110111110100 L
b111111101101010110010011100110 I
b111111101101001111110111110100 U
b111011010011011110001100100010 S
1W
b10 Q
b0 g
b0 F
b0 T
b0 E
b0 R
0G
0V
b11 O
b1 N
b0x d
0(
#140000
b111111101101001111110111110100 U
b111011010011011110001100100010 S
1W
0"
0:
b0 #
b0 *
b0 =
b0 C
b0 Y
b0 3
1(
#145000
1;
b111111101101010110010011100110 4
b101101010110010011100110 6
b1000 <
1.
b101101001111110111110100 2
b110011011110001 1
b1111111 /
b0x g
1$
b111111101101001111110111110100 &
b111111101101001111110111110100 +
b111111101101001111110111110100 A
b111011010011011110001100100010 '
b111011010011011110001100100010 ,
b111011010011011110001100100010 @
b0 U
b0 S
0W
b0 d
b111111101101001111110111110100 F
b111111101101001111110111110100 T
b111011010011011110001100100010 E
b111011010011011110001100100010 R
1G
1V
b10 N
0(
#150000
b100 P
b1 Q
1"
1:
b111111101101010110010011100110 #
b111111101101010110010011100110 *
b111111101101010110010011100110 =
b111111101101010110010011100110 C
b111111101101010110010011100110 Y
b111111101101010110010011100110 3
1(
#155000
0;
b0 4
b0 &
b0 +
b0 A
b0 '
b0 ,
b0 @
0$
b111111101101001111110111110100 U
b111011010011011110001100100010 S
1W
b10 Q
b0 g
b0 F
b0 T
b0 E
b0 R
0G
0V
b100 O
b1 N
b0x d
0(
#160000
b111111101101001111110111110100 U
b111011010011011110001100100010 S
1W
0"
0:
b0 #
b0 *
b0 =
b0 C
b0 Y
b0 3
1(
#165000
1;
b111111101101010110010011100110 4
b101101010110010011100110 6
b1000 <
1.
b110011011110001 1
b1111111 /
b0x g
1$
b111111101101001111110111110100 &
b111111101101001111110111110100 +
b111111101101001111110111110100 A
b111011010011011110001100100010 '
b111011010011011110001100100010 ,
b111011010011011110001100100010 @
b0 U
b0 S
0W
b0 d
b111111101101001111110111110100 F
b111111101101001111110111110100 T
b111011010011011110001100100010 E
b111011010011011110001100100010 R
1G
1V
b10 N
0(
#170000
b101 P
b1 Q
1"
1:
b111111101101010110010011100110 #
b111111101101010110010011100110 *
b111111101101010110010011100110 =
b111111101101010110010011100110 C
b111111101101010110010011100110 Y
b111111101101010110010011100110 3
1(
#175000
0;
b0 4
b0 &
b0 +
b0 A
b0 '
b0 ,
b0 @
0$
b10111011010011011110001100100010 M
b111111101101001001011100000010 I
b111111101101001111110111110100 U
b10111011010011011110001100100010 S
1W
b10 Q
b0 g
b0 F
b0 T
b0 E
b0 R
0G
0V
b101 O
b1 N
b0x d
0(
#180000
b111111101101001111110111110100 U
b10111011010011011110001100100010 S
1W
0"
0:
b0 #
b0 *
b0 =
b0 C
b0 Y
b0 3
1(
#185000
1;
b111111101101001001011100000010 4
b101101001001011100000010 6
b1000 <
1.
b110011011110001 1
b1111111 /
b0x g
1$
b111111101101001111110111110100 &
b111111101101001111110111110100 +
b111111101101001111110111110100 A
b10111011010011011110001100100010 '
b10111011010011011110001100100010 ,
b10111011010011011110001100100010 @
b0 U
b0 S
0W
b0 d
b111111101101001111110111110100 F
b111111101101001111110111110100 T
b10111011010011011110001100100010 E
b10111011010011011110001100100010 R
1G
1V
b10 N
0(
#190000
b110 P
b1 Q
1"
1:
b111111101101001001011100000010 #
b111111101101001001011100000010 *
b111111101101001001011100000010 =
b111111101101001001011100000010 C
b111111101101001001011100000010 Y
b111111101101001001011100000010 3
1(
#195000
0;
b0 4
b0 &
b0 +
b0 A
b0 '
b0 ,
b0 @
0$
b111011010011011110001100100010 M
b10111111101101001111110111110100 L
b10111111101101001001011100000010 I
b10111111101101001111110111110100 U
b111011010011011110001100100010 S
1W
b10 Q
b0 g
b0 F
b0 T
b0 E
b0 R
0G
0V
b110 O
b1 N
b0x d
0(
#200000
b10111111101101001111110111110100 U
b111011010011011110001100100010 S
1W
0"
0:
b0 #
b0 *
b0 =
b0 C
b0 Y
b0 3
1(
#205000
1;
b10111111101101001001011100000010 4
19
b101101001001011100000010 6
b1000 <
1.
b110011011110001 1
b1111111 /
b0x g
1$
b10111111101101001111110111110100 &
b10111111101101001111110111110100 +
b10111111101101001111110111110100 A
b111011010011011110001100100010 '
b111011010011011110001100100010 ,
b111011010011011110001100100010 @
b0 U
b0 S
0W
b0 d
b10111111101101001111110111110100 F
b10111111101101001111110111110100 T
b111011010011011110001100100010 E
b111011010011011110001100100010 R
1G
1V
b10 N
0(
#210000
b111 P
b1 Q
1"
1:
b10111111101101001001011100000010 #
b10111111101101001001011100000010 *
b10111111101101001001011100000010 =
b10111111101101001001011100000010 C
b10111111101101001001011100000010 Y
b10111111101101001001011100000010 3
1(
#215000
0;
b0 4
b0 &
b0 +
b0 A
b0 '
b0 ,
b0 @
0$
b10111111101101001111110111110100 M
b111101000000001010110111110101 L
b10111111101100001111100010000100 I
b111101000000001010110111110101 U
b10111111101101001111110111110100 S
1W
b10 Q
b0 g
b0 F
b0 T
b0 E
b0 R
0G
0V
b111 O
b1 N
b0x d
0(
#220000
b111101000000001010110111110101 U
b10111111101101001111110111110100 S
1W
0"
0:
b0 #
b0 *
b0 =
b0 C
b0 Y
b0 3
1(
#225000
1;
b10111111101100001111100010000100 4
b101100001111100010000100 6
b100 <
1.
b1000000010101101111 2
b101101001111110111110100 1
b1111111 0
b0x g
1$
b111101000000001010110111110101 &
b111101000000001010110111110101 +
b111101000000001010110111110101 A
b10111111101101001111110111110100 '
b10111111101101001111110111110100 ,
b10111111101101001111110111110100 @
b0 U
b0 S
0W
b0 d
b111101000000001010110111110101 F
b111101000000001010110111110101 T
b10111111101101001111110111110100 E
b10111111101101001111110111110100 R
1G
1V
b10 N
0(
#230000
b1000 P
b1 Q
1"
1:
b10111111101100001111100010000100 #
b10111111101100001111100010000100 *
b10111111101100001111100010000100 =
b10111111101100001111100010000100 C
b10111111101100001111100010000100 Y
b10111111101100001111100010000100 3
1(
